autocompleter/__init__.py
autocompleter/main.py
django_autocompleter-0.0.7.dist-info/LICENSE.md
django_autocompleter-0.0.7.dist-info/METADATA
django_autocompleter-0.0.7.dist-info/WHEEL
django_autocompleter-0.0.7.dist-info/top_level.txt
django_autocompleter-0.0.7.dist-info/RECORD
