Metadata-Version: 2.1
Name: django-autocompleter
Version: 0.0.7
Summary: UNKNOWN
Home-page: https://github.com/stanley0707/django_autocomleter.git
Author: Stas Shilov
Author-email: shilowstanisalw@gamail.com
License: UNKNOWN
Platform: UNKNOWN
Classifier: Programming Language :: Python :: 3
Classifier: License :: OSI Approved :: MIT License
Classifier: Operating System :: OS Independent
